sc.embedder-1.2b2-py2.7-nspkg.pth
sc/embedder/__init__.py
sc/embedder/adapters.py
sc/embedder/config.py
sc/embedder/configure.zcml
sc/embedder/interfaces.py
sc/embedder/logger.py
sc/embedder/profiles.zcml
sc/embedder/setuphandlers.py
sc/embedder/skins.zcml
sc/embedder/testing.py
sc/embedder/utility.py
sc/embedder/utils.py
sc/embedder/Extensions/Install.py
sc/embedder/Extensions/__init__.py
sc/embedder/browser/__init__.py
sc/embedder/browser/configure.zcml
sc/embedder/browser/views.py
sc/embedder/content/__init__.py
sc/embedder/content/configure.zcml
sc/embedder/content/embedder.py
sc/embedder/content/image_input.pt
sc/embedder/content/templates/edit.pt
sc/embedder/content/templates/embeddervideojs.pt
sc/embedder/content/templates/sc.embedder.pt
sc/embedder/content/templates/view.pt
sc/embedder/locales/manual.pot
sc/embedder/locales/plone.pot
sc/embedder/locales/rebuildPo.sh
sc/embedder/locales/sc.embedder.pot
sc/embedder/locales/tinymce.pot
sc/embedder/locales/es/LC_MESSAGES/plone.po
sc/embedder/locales/es/LC_MESSAGES/sc.embedder.po
sc/embedder/locales/es/LC_MESSAGES/tinymce.po
sc/embedder/locales/it/LC_MESSAGES/sc.embedder.po
sc/embedder/locales/it/LC_MESSAGES/tinymce.po
sc/embedder/locales/pt_BR/LC_MESSAGES/plone.po
sc/embedder/locales/pt_BR/LC_MESSAGES/sc.embedder.po
sc/embedder/locales/pt_BR/LC_MESSAGES/tinymce.po
sc/embedder/profiles/default/browserlayer.xml
sc/embedder/profiles/default/cssregistry.xml
sc/embedder/profiles/default/import_steps.xml
sc/embedder/profiles/default/metadata.xml
sc/embedder/profiles/default/registry.xml
sc/embedder/profiles/default/rolemap.xml
sc/embedder/profiles/default/sc.embedder-default.txt
sc/embedder/profiles/default/skins.xml
sc/embedder/profiles/default/tinymce.xml
sc/embedder/profiles/default/types.xml
sc/embedder/profiles/default/types/sc.embedder.xml
sc/embedder/profiles/uninstall/sc.content.embedder-uninstall.txt
sc/embedder/skins/images/embedder.png
sc.embedder-1.2b2.dist-info/DESCRIPTION.rst
sc.embedder-1.2b2.dist-info/METADATA
sc.embedder-1.2b2.dist-info/RECORD
sc.embedder-1.2b2.dist-info/WHEEL
sc.embedder-1.2b2.dist-info/entry_points.txt
sc.embedder-1.2b2.dist-info/metadata.json
sc.embedder-1.2b2.dist-info/namespace_packages.txt
sc.embedder-1.2b2.dist-info/top_level.txt
