Metadata-Version: 2.0
Name: sc.embedder
Version: 1.2b2
Summary: This packages contains a Dexterity-based content type that 
Home-page: http://www.simplesconsultoria.com.br
Author: Simples Consultoria
Author-email: products@simplesconsultoria.com.br
License: GPLv2
Keywords: multimedia video audio oembed plone embed embedder
Platform: UNKNOWN
Classifier: Development Status :: 4 - Beta
Classifier: Environment :: Web Environment
Classifier: Framework :: Plone
Classifier: Framework :: Plone :: 4.2
Classifier: Framework :: Plone :: 4.3
Classifier: Intended Audience :: End Users/Desktop
Classifier: Intended Audience :: System Administrators
Classifier: License :: OSI Approved :: GNU General Public License v2 (GPLv2)
Classifier: Operating System :: OS Independent
Classifier: Programming Language :: JavaScript
Classifier: Programming Language :: Python
Classifier: Programming Language :: Python :: 2.7
Classifier: Topic :: Internet :: WWW/HTTP
Classifier: Topic :: Internet :: WWW/HTTP :: Dynamic Content
Classifier: Topic :: Multimedia
Classifier: Topic :: Office/Business
Classifier: Topic :: Software Development :: Libraries :: Python Modules
Requires-Dist: Products.CMFPlone (>=4.2)
Requires-Dist: Products.GenericSetup
Requires-Dist: Products.TinyMCE
Requires-Dist: collective.dexteritytextindexer
Requires-Dist: lxml
Requires-Dist: plone.api
Requires-Dist: plone.app.content
Requires-Dist: plone.app.dexterity
Requires-Dist: plone.app.textfield
Requires-Dist: plone.autoform
Requires-Dist: plone.dexterity
Requires-Dist: plone.formwidget.namedfile
Requires-Dist: plone.namedfile[blobs]
Requires-Dist: plone.supermodel
Requires-Dist: plone.uuid
Requires-Dist: python-oembed
Requires-Dist: requests
Requires-Dist: setuptools
Requires-Dist: z3c.form
Requires-Dist: zope.component
Requires-Dist: zope.event
Requires-Dist: zope.i18nmessageid
Requires-Dist: zope.interface
Requires-Dist: zope.publisher
Requires-Dist: zope.schema
Provides-Extra: test
Requires-Dist: Products.statusmessages; extra == 'test'
Requires-Dist: httmock; extra == 'test'
Requires-Dist: plone.app.robotframework; extra == 'test'
Requires-Dist: plone.app.testing[robot]; extra == 'test'
Requires-Dist: plone.browserlayer; extra == 'test'
Requires-Dist: plone.testing; extra == 'test'
Requires-Dist: robotframework-selenium2accessibility; extra == 'test'
Requires-Dist: robotsuite; extra == 'test'
